akipy-1.3.5.dist-info/METADATA
akipy-1.3.5.dist-info/WHEEL
akipy-1.3.5.dist-info/entry_points.txt
akipy-1.3.5.dist-info/licenses/LICENSE
akipy/__init__.py
akipy/akinator.py
akipy/async_akinator.py
akipy/dicts.py
akipy/exceptions.py
akipy/py.typed
akipy/utils.py
akipy-1.3.5.dist-info/RECORD
