Metadata-Version: 2.1
Name: akipy
Version: 1.3.5
Summary: A Python library wrapper for Akinator
Author-Email: advnpzn <adenosinetp10@protonmail.com>
Classifier: License :: OSI Approved :: MIT License
Classifier: Programming Language :: Python
Classifier: Programming Language :: Python :: 3
Project-URL: Bug Tracker, https://github.com/advnpzn/akipy/issues
Project-URL: repository, https://github.com/advnpzn/akipy
Requires-Python: <4.0,>=3.12
Requires-Dist: aiohttp>=3.13.2
Requires-Dist: httpx<1.0.0,>=0.28.1
Requires-Dist: pytest>=8.4.2
Requires-Dist: pytest-asyncio>=1.2.0
Requires-Dist: pytest-mock>=3.15.1
Requires-Dist: ruff>=0.9.3
